dist_classicrl/__init__.py
dist_classicrl/_version.py
dist_classicrl/_version.pyi
dist_classicrl/utils.py
dist_classicrl/algorithms/__init__.py
dist_classicrl/algorithms/base_algorithms/__init__.py
dist_classicrl/algorithms/base_algorithms/q_learning_optimal.py
dist_classicrl/algorithms/buffers/__init__.py
dist_classicrl/algorithms/buffers/experience_replay.py
dist_classicrl/algorithms/runtime/__init__.py
dist_classicrl/algorithms/runtime/base_runtime.py
dist_classicrl/algorithms/runtime/parallel_runtime.py
dist_classicrl/algorithms/runtime/q_learning_async_dist.py
dist_classicrl/algorithms/runtime/single_thread_runtime.py
dist_classicrl/benchmarks/README.md
dist_classicrl/benchmarks/__init__.py
dist_classicrl/benchmarks/analyze_throughput_benchmarks.py
dist_classicrl/benchmarks/precommit_throughput_benchmarks.sh
dist_classicrl/benchmarks/run_comprehensive_throughput_benchmarks.sh
dist_classicrl/benchmarks/run_throughput_benchmarks_generic.sh
dist_classicrl/benchmarks/throughput_benchmark.py
dist_classicrl/environments/__init__.py
dist_classicrl/environments/custom_env.py
dist_classicrl/environments/rigged_two_armed_bandit.py
dist_classicrl/environments/tiktaktoe_mod.py
dist_classicrl/old/__init__.py
dist_classicrl/old/parallel_wrapper.py
dist_classicrl/old/q_learning_list.py
dist_classicrl/old/q_learning_numpy.py
dist_classicrl/old/q_learning_optimal_petting_zoo.py
dist_classicrl/old/q_learning_petting_zoo.py
dist_classicrl/schedules/__init__.py
dist_classicrl/schedules/base_schedules.py
dist_classicrl/schedules/constant_schedule.py
dist_classicrl/schedules/exponential_schedule.py
dist_classicrl/schedules/linear_schedule.py
dist_classicrl/wrappers/__init__.py
dist_classicrl/wrappers/dummy_vec_wrapper.py
dist_classicrl/wrappers/flatten_multidiscrete_wrapper.py
dist_classicrl-0.1.17.dist-info/licenses/AUTHORS.rst
dist_classicrl-0.1.17.dist-info/licenses/LICENSE.txt
dist_classicrl-0.1.17.dist-info/METADATA
dist_classicrl-0.1.17.dist-info/WHEEL
dist_classicrl-0.1.17.dist-info/top_level.txt
dist_classicrl-0.1.17.dist-info/RECORD
