Metadata-Version: 2.4
Name: dist_classicrl
Version: 0.1.17
Summary: A high-performance Python package for distributed classical reinforcement learning algorithms with support for single-threaded, parallel, and MPI-distributed Q-Learning training.
Author-email: Javier Moralejo Piñas <j.moralejo.pinas@gmail.com>
License: MIT
Project-URL: Homepage, https://github.com/j-moralejo-pinas/dist_classicrl
Project-URL: Source, https://github.com/j-moralejo-pinas/dist_classicrl
Project-URL: Tracker, https://github.com/j-moralejo-pinas/dist_classicrl/issues
Classifier: Programming Language :: Python :: 3
Classifier: License :: OSI Approved :: MIT License
Classifier: Operating System :: OS Independent
Requires-Python: >=3.13
License-File: LICENSE.txt
License-File: AUTHORS.rst
Requires-Dist: gymnasium
Requires-Dist: matplotlib
Requires-Dist: mpi4py
Requires-Dist: numpy
Provides-Extra: dev
Requires-Dist: pyright; extra == "dev"
Requires-Dist: pre-commit; extra == "dev"
Requires-Dist: ruff; extra == "dev"
Requires-Dist: pydoclint; extra == "dev"
Requires-Dist: docformatter; extra == "dev"
Requires-Dist: pytest; extra == "dev"
Requires-Dist: pytest-cov; extra == "dev"
Requires-Dist: pyupgrade; extra == "dev"
Provides-Extra: test
Requires-Dist: pytest; extra == "test"
Requires-Dist: pytest-cov; extra == "test"
Provides-Extra: code-quality
Requires-Dist: ruff; extra == "code-quality"
Requires-Dist: pydoclint; extra == "code-quality"
Requires-Dist: pyright; extra == "code-quality"
Provides-Extra: format
Requires-Dist: ruff; extra == "format"
Requires-Dist: docformatter; extra == "format"
Requires-Dist: pyupgrade; extra == "format"
Provides-Extra: docs
Requires-Dist: sphinx; extra == "docs"
Requires-Dist: sphinx-autoapi; extra == "docs"
Requires-Dist: sphinx_rtd_theme; extra == "docs"
Requires-Dist: sphinxcontrib-napoleon; extra == "docs"
Dynamic: license-file
